{
    "Setting":[
    "./Настройки/Account.json",
    "./Настройки/Action.json",
    "./Настройки/Category.json",
    "./Настройки/Event-filters.json",
    "./Настройки/Global-var.json",
    "./Настройки/Incidents.json",
    "./Настройки/license.json",
    "./Настройки/Playbook.json",
    "./Настройки/Script.json",
    "./Настройки/Label.json",
    "./Настройки/Alert.json",
    "./Настройки/Custom-dashboard.json",
    "./Настройки/Upload.json",
    "Настройки/Policy.json",
    "Настройки/Agent.json",
    "Настройки/Debug.json",
    "Настройки/Calculation.json",
    "Настройки/Postgres_activity.json",
    "Настройки/Risk.json"
],
    "Object":[
    "Объекты/Filse.json",
    "Объекты/User.json",
    "Объекты/User_card.json",
    "Объекты/Mailbox.json",
    "Объекты/Events.json",
    "Объекты/Alerts.json",
    "Объекты/Сomputers.json",
    "Объекты/Alert_card.json",
    "Объекты/Mailbox_card.json",
    "Объекты/Upload.json",
    "Объекты/Events_card.json",
    "Объекты/File_card.json"
    ],
    "Autorization":[
        "Авторизация/Autorization.json"
    ],
    "Risk":[
        "Риск/mailbox_risk.json",
        "Риск/file_and_folder_risk.json",
        "Риск/file_risk.json"
    ],
    "Bell":[
        "Колокольчик_в_шапке_сайта/file_recalc.json",
        "Колокольчик_в_шапке_сайта/recalc-analytics.json",
        "Колокольчик_в_шапке_сайта/mailbox_recalc-analytics.json"
    ]
}