{
    "Title": "",
    "Name": "/identity/right/json",
    "Title_name": "Права",
    "Format": "raw",
    "GET": [
        "GET",
        "POST",
        "DELETE"
    ],
    "GET_Text": " запросы",
    "URL_ID_DELETE": "/22",
    "URL_ID_POST": "",
    "DOP_URL": "",
    "Response": [
        {
            "GET": {
                "count": 287,
                "items": [
                    {
                        "id": 2,
                        "created_at": "2014-03-19T16:06:10+03:00",
                        "updated_at": "2022-06-28T12:09:09.558161+03:00",
                        "deleted_at": null,
                        "service_id": 1,
                        "service": {
                            "id": 1,
                            "created_at": "2021-07-02T10:48:07.270707+03:00",
                            "updated_at": "2022-06-28T12:09:09.546408+03:00",
                            "deleted_at": null,
                            "type": "ad",
                            "name": "MKVS-DOMAIN-P",
                            "description": "",
                            "owner": "",
                            "admin": "",
                            "specific": null,
                            "history": null,
                            "upload_id": 0,
                            "components": null,
                            "fields": null,
                            "dn": "",
                            "accounts": null,
                            "rights": null,
                            "relations": null
                        },
                        "service_name": "MKVS-DOMAIN-P",
                        "service_type": "ad",
                        "name": "Пользователи",
                        "history": null,
                        "dcap_id": "",
                        "component_id": 0,
                        "component": {
                            "id": 0,
                            "created_at": "0001-01-01T00:00:00Z",
                            "updated_at": "0001-01-01T00:00:00Z",
                            "deleted_at": null,
                            "service_id": 0,
                            "name": "",
                            "description": "",
                            "num_rights": 0,
                            "num_accounts": 0,
                            "service_name": "",
                            "fields": null,
                            "dn": ""
                        },
                        "component_name": "",
                        "curator": 0,
                        "expired_at": "0001-01-01T03:00:00+03:00",
                        "count_problems": 1,
                        "has_opened_requests": true,
                        "requests": null,
                        "employees": null,
                        "accounts": null,
                        "rights": null,
                        "fields": [],
                        "dn": "CN=Пользователи,CN=Builtin,DC=MKVS-Domain-P,DC=ru",
                        "relations": null,
                        "num_rights": 0,
                        "num_accounts": 0,
                        "num_employees": 0
                    },
                    {
                        "id": 3,
                        "created_at": "2014-03-19T16:06:10+03:00",
                        "updated_at": "2022-06-28T12:09:09.560027+03:00",
                        "deleted_at": null,
                        "service_id": 1,
                        "service": {
                            "id": 1,
                            "created_at": "2021-07-02T10:48:07.270707+03:00",
                            "updated_at": "2022-06-28T12:09:09.546408+03:00",
                            "deleted_at": null,
                            "type": "ad",
                            "name": "MKVS-DOMAIN-P",
                            "description": "",
                            "owner": "",
                            "admin": "",
                            "specific": null,
                            "history": null,
                            "upload_id": 0,
                            "components": null,
                            "fields": null,
                            "dn": "",
                            "accounts": null,
                            "rights": null,
                            "relations": null
                        },
                        "service_name": "MKVS-DOMAIN-P",
                        "service_type": "ad",
                        "name": "Гости",
                        "history": null,
                        "dcap_id": "",
                        "component_id": 0,
                        "component": {
                            "id": 0,
                            "created_at": "0001-01-01T00:00:00Z",
                            "updated_at": "0001-01-01T00:00:00Z",
                            "deleted_at": null,
                            "service_id": 0,
                            "name": "",
                            "description": "",
                            "num_rights": 0,
                            "num_accounts": 0,
                            "service_name": "",
                            "fields": null,
                            "dn": ""
                        },
                        "component_name": "",
                        "curator": 0,
                        "expired_at": "0001-01-01T03:00:00+03:00",
                        "count_problems": 1,
                        "has_opened_requests": true,
                        "requests": null,
                        "employees": null,
                        "accounts": null,
                        "rights": null,
                        "fields": [],
                        "dn": "CN=Гости,CN=Builtin,DC=MKVS-Domain-P,DC=ru",
                        "relations": null,
                        "num_rights": 0,
                        "num_accounts": 0,
                        "num_employees": 0
                    }
                ]
            },
            "POST": {
                "data": {
                    "id": 323,
                    "created_at": "2022-08-05T10:09:36.5982037+03:00",
                    "updated_at": "2022-08-05T10:09:36.5982037+03:00",
                    "deleted_at": null,
                    "service_id": 10,
                    "service": {
                        "id": 0,
                        "created_at": "0001-01-01T00:00:00Z",
                        "updated_at": "0001-01-01T00:00:00Z",
                        "deleted_at": null,
                        "type": "",
                        "name": "",
                        "description": "",
                        "owner": "",
                        "admin": "",
                        "specific": null,
                        "history": null,
                        "upload_id": 0,
                        "components": null,
                        "fields": null,
                        "dn": "",
                        "accounts": null,
                        "rights": null,
                        "relations": null
                    },
                    "service_name": "",
                    "service_type": "",
                    "name": "Misha",
                    "history": null,
                    "dcap_id": "",
                    "component_id": 0,
                    "component": {
                        "id": 0,
                        "created_at": "0001-01-01T00:00:00Z",
                        "updated_at": "0001-01-01T00:00:00Z",
                        "deleted_at": null,
                        "service_id": 0,
                        "name": "",
                        "description": "",
                        "num_rights": 0,
                        "num_accounts": 0,
                        "service_name": "",
                        "fields": null,
                        "dn": ""
                    },
                    "component_name": "",
                    "curator": 360,
                    "expired_at": "2025-01-30T20:00:00Z",
                    "count_problems": 0,
                    "has_opened_requests": false,
                    "requests": null,
                    "employees": null,
                    "accounts": null,
                    "rights": null,
                    "fields": null,
                    "dn": "Autotest23",
                    "relations": null
                }
            }
        }
    ],
    "Req": [
        {
            "POST": {
                "component_id": "0",
                "curator": 360,
                "dn": "Autotest23",
                "expired_at": "2025-01-30T20:00:00.000Z",
                "name": "Misha",
                "service_id": "10"
            },
            "DELETE": {
                "Пример": "http://dev.makves.ru:8000/identity/resource/json/id",
                "Пример со значением": "http://dev.makves.ru:8000/identity/resource/json/22"
            }
        }
    ],
    "Text": {
        "id": "В API 'Права' получить id и указать его в ссылке",
        "component_id": "Компонент",
        "curator": "Куратор",
        "dn": "Уникальное имя",
        "expired_at": "Дата '2025-01-30T20:00:00.000Z'",
        "name": "Имя",
        "service_id": "Сервис"
    }
}